azure_functions/kafka/__init__.py
azure_functions/kafka/_kafka.py
azure_functions/kafka/kafka.py
azure_functions_kafka_binding-1.0.1.dist-info/LICENSE
azure_functions_kafka_binding-1.0.1.dist-info/METADATA
azure_functions_kafka_binding-1.0.1.dist-info/WHEEL
azure_functions_kafka_binding-1.0.1.dist-info/top_level.txt
azure_functions_kafka_binding-1.0.1.dist-info/RECORD
