Metadata-Version: 2.1
Name: azure-functions-kafka-binding
Version: 1.0.1
Summary: UNKNOWN
Home-page: https://github.com/Azure/azure-functions-kafka-extension
Author: Microsoft Corporation
License: MIT License
Platform: UNKNOWN
Classifier: Development Status :: 3 - Alpha
Classifier: Programming Language :: Python :: 3.6
Classifier: Operating System :: OS Independent
Classifier: License :: OSI Approved :: MIT License
Requires-Dist: azure-functions-worker
